microsoft_agents/storage/cosmos/__init__.py
microsoft_agents/storage/cosmos/cosmos_db_storage.py
microsoft_agents/storage/cosmos/cosmos_db_storage_config.py
microsoft_agents/storage/cosmos/key_ops.py
microsoft_agents/storage/cosmos/errors/__init__.py
microsoft_agents/storage/cosmos/errors/error_resources.py
microsoft_agents_storage_cosmos-0.7.0.dist-info/licenses/LICENSE
microsoft_agents_storage_cosmos-0.7.0.dist-info/METADATA
microsoft_agents_storage_cosmos-0.7.0.dist-info/WHEEL
microsoft_agents_storage_cosmos-0.7.0.dist-info/top_level.txt
microsoft_agents_storage_cosmos-0.7.0.dist-info/RECORD
