Metadata-Version: 2.4
Name: microsoft-agents-storage-cosmos
Version: 0.7.0
Summary: A Cosmos DB storage library for Microsoft Agents
Author: Microsoft Corporation
License-Expression: MIT
Project-URL: Homepage, https://github.com/microsoft/Agents
Classifier: Programming Language :: Python :: 3
Classifier: Programming Language :: Python :: 3.10
Classifier: Programming Language :: Python :: 3.11
Classifier: Programming Language :: Python :: 3.12
Classifier: Programming Language :: Python :: 3.13
Classifier: Programming Language :: Python :: 3.14
Classifier: Operating System :: OS Independent
Requires-Python: >=3.10
License-File: LICENSE
Requires-Dist: microsoft-agents-hosting-core==0.7.0
Requires-Dist: azure-core
Requires-Dist: azure-cosmos
Requires-Dist: azure-identity
Dynamic: license-file
Dynamic: requires-dist
